jupyter_rtc_core/__init__.py
jupyter_rtc_core/_version.py
jupyter_rtc_core/app.py
jupyter_rtc_core/handlers.py
jupyter_rtc_core/session_manager.py
jupyter_rtc_core/kernels/__init__.py
jupyter_rtc_core/kernels/kernel_client.py
jupyter_rtc_core/kernels/kernel_manager.py
jupyter_rtc_core/kernels/multi_kernel_manager.py
jupyter_rtc_core/kernels/states.py
jupyter_rtc_core/kernels/utils.py
jupyter_rtc_core/kernels/websocket_connection.py
jupyter_rtc_core/outputs/__init__.py
jupyter_rtc_core/outputs/handlers.py
jupyter_rtc_core/outputs/manager.py
jupyter_rtc_core/outputs/output_processor.py
jupyter_rtc_core/rooms/__init__.py
jupyter_rtc_core/rooms/mock_yroom.py
jupyter_rtc_core/rooms/yroom.py
jupyter_rtc_core/rooms/yroom_file_api.py
jupyter_rtc_core/rooms/yroom_manager.py
jupyter_rtc_core/tests/__init__.py
jupyter_rtc_core/tests/test_handlers.py
jupyter_rtc_core/tests/test_output_processor.py
jupyter_rtc_core/tests/test_outputs_manager.py
jupyter_rtc_core/tests/test_yroom_file_api.py
jupyter_rtc_core/tests/mocks/mock_plaintext.txt
jupyter_rtc_core/websockets/__init__.py
jupyter_rtc_core/websockets/clients.py
jupyter_rtc_core/websockets/yroom_ws.py
jupyter_rtc_core-0.1.0a3.data/data/etc/jupyter/jupyter_server_config.d/jupyter_rtc_core.json
jupyter_rtc_core-0.1.0a3.data/data/share/jupyter/labextensions/@jupyter/rtc-core/package.json
jupyter_rtc_core-0.1.0a3.data/data/share/jupyter/labextensions/@jupyter/rtc-core/schemas/@jupyter/rtc-core/package.json.orig
jupyter_rtc_core-0.1.0a3.data/data/share/jupyter/labextensions/@jupyter/rtc-core/schemas/@jupyter/rtc-core/plugin.json
jupyter_rtc_core-0.1.0a3.data/data/share/jupyter/labextensions/@jupyter/rtc-core/static/381.57f5c5d84599eff6b149.js
jupyter_rtc_core-0.1.0a3.data/data/share/jupyter/labextensions/@jupyter/rtc-core/static/388.2d30ce2007a522c1b266.js
jupyter_rtc_core-0.1.0a3.data/data/share/jupyter/labextensions/@jupyter/rtc-core/static/506.f30fec4a5f7f5943a390.js
jupyter_rtc_core-0.1.0a3.dist-info/METADATA
jupyter_rtc_core-0.1.0a3.dist-info/WHEEL
jupyter_rtc_core-0.1.0a3.dist-info/licenses/LICENSE
jupyter_rtc_core-0.1.0a3.dist-info/RECORD
